setup.py
core/__init__.py
slg_core.egg-info/PKG-INFO
slg_core.egg-info/SOURCES.txt
slg_core.egg-info/dependency_links.txt
slg_core.egg-info/requires.txt
slg_core.egg-info/top_level.txt