Metadata-Version: 1.0
Name: slg-core
Version: 0.1
Summary: Slingshot Core Framework
Home-page: http://git.prod.skyscanner.local/slingshot/slingshot-core.git
Author: UNKNOWN
Author-email: UNKNOWN
License: UNKNOWN
Platform: UNKNOWN
